cloud_training/__init__.py
cloud_training/abstract_command.py
cloud_training/aws.py
cloud_training/configure.py
cloud_training/project_command.py
cloud_training/utils.py
cloud_training/commands/__init__.py
cloud_training/commands/configure.py
cloud_training/commands/shutdown.py
cloud_training/commands/spot_price.py
cloud_training/commands/sync_session.py
cloud_training/commands/train.py
cloud_training/data/default-launch-specification.json
cloud_training/data/launch-specification.json
cloud_training/data/unzip.py
cloud_training/data/user_data.sh
cloud_training-0.1.0.data/scripts/cloud-training
cloud_training-0.1.0.data/scripts/cloud_training
cloud_training-0.1.0.dist-info/DESCRIPTION.rst
cloud_training-0.1.0.dist-info/METADATA
cloud_training-0.1.0.dist-info/RECORD
cloud_training-0.1.0.dist-info/WHEEL
cloud_training-0.1.0.dist-info/metadata.json
cloud_training-0.1.0.dist-info/top_level.txt
